[
  {
    "text": "Dr. Kh. Nafiz Rahman is a Orthopedic Surgeon with 16 years of experience. He holds the qualifications MBBS, BCS (Health), D-Ortho (BSMMU), AO Trauma (Fellow). Currently practicing at Mirpur General Hospital and Diagnostic Center located at R#10, H#16, Rupnogor Residential Area, Beside of Monipur School), Mirpur, Dhaka., Mirpur, Dhaka, 1216, Bangladesh. Availability: Saturday to Thursday: 06:00 PM - 09:00 PM; Friday: Off. Expertise includes Regenerative Technique, Epidural Transformational Injection, Facetal Injection, Robotic Calipers / Injections, Neck and Back pain Clinic, Spine Conservative, Spine 3D Printing, Joint Pain Treatment, Endoscopic Disc Surgery, Back Pain, Neck Pain.For more information about Mirpur General Hospital and Diagnostic Center, please visit https://www.doctorspedia.co/hospital/mirpur-general-hospital-and-diagnostic-center",
    "metadata": {
      "id": "67fe041313b6d75e7dd157b4",
      "name": "Dr. Kh. Nafiz Rahman",
      "specialization": "Orthopedic Surgeon",
      "yoe": 16,
      "tags": "['Regenerative Technique', 'Epidural Transformational Injection', 'Facetal Injection', 'Robotic Calipers / Injections', 'Neck and Back pain Clinic', 'Spine Conservative', 'Spine 3D Printing', 'Joint Pain Treatment', 'Endoscopic Disc Surgery', 'Back Pain', 'Neck Pain']",
      "designation": "MBBS, BCS (Health), D-Ortho (BSMMU), AO Trauma (Fellow)",
      "hospital": "Mirpur General Hospital and Diagnostic Center",
      "hospital_address": "R#10, H#16, Rupnogor Residential Area, Beside of Monipur School), Mirpur, Dhaka., Mirpur, Dhaka, 1216, Bangladesh",
      "hospital_url": "https://www.doctorspedia.co/hospital/mirpur-general-hospital-and-diagnostic-center",
      "availability": "['Saturday to Thursday: 06:00 PM - 09:00 PM', 'Friday: Off']"
    }
  },
  {
    "text": "Prof. Dr. A.K.M. Jahangir Alam is a Orthopedic Surgeon with 24 years of experience. He holds the qualifications MBBS, DCM, MS (Ortho). Currently practicing at Mirpur General Hospital and Diagnostic Center located at R#10, H#16, Rupnogor Residential Area, Beside of Monipur School), Mirpur, Dhaka., Mirpur, Dhaka, 1216, Bangladesh. Availability: Saturday to Thursday: 06:00 PM - 08:00 PM; Friday: Off. Expertise includes Congenital and acquired deformity correction, Spinal Cord Injury Treatment, Keyhole-Sutureless Spinal surgeries, Spinal Rehabilitation Technique, Spine Conservative Management / Nonsurgical Technique, Spine Dynamic stabilisation, Non Fusional spine surgical Technique.For more information about Mirpur General Hospital and Diagnostic Center, please visit https://www.doctorspedia.co/hospital/mirpur-general-hospital-and-diagnostic-center",
    "metadata": {
      "id": "67fe041313b6d75e7dd157b5",
      "name": "Prof. Dr. A.K.M. Jahangir Alam",
      "specialization": "Orthopedic Surgeon",
      "yoe": 24,
      "tags": "['Congenital and acquired deformity correction', 'Spinal Cord Injury Treatment', 'Keyhole-Sutureless Spinal surgeries', 'Spinal Rehabilitation Technique', 'Spine Conservative Management / Nonsurgical Technique', 'Spine Dynamic stabilisation', 'Non Fusional spine surgical Technique']",
      "designation": "MBBS, DCM, MS (Ortho)",
      "hospital": "Mirpur General Hospital and Diagnostic Center",
      "hospital_address": "R#10, H#16, Rupnogor Residential Area, Beside of Monipur School), Mirpur, Dhaka., Mirpur, Dhaka, 1216, Bangladesh",
      "hospital_url": "https://www.doctorspedia.co/hospital/mirpur-general-hospital-and-diagnostic-center",
      "availability": "['Saturday to Thursday: 06:00 PM - 08:00 PM', 'Friday: Off']"
    }
  },
  {
    "text": "Dr. Lt. Col. Md. Mahbub Ali is a Orthopedic Surgeon with 15 years of experience. He holds the qualifications MBBS, MS (Ortho Surgery). Currently practicing at Mirpur General Hospital and Diagnostic Center located at R#10, H#16, Rupnogor Residential Area, Beside of Monipur School), Mirpur, Dhaka., Mirpur, Dhaka, 1216, Bangladesh. Availability: Saturday to Thursday: 06:00 PM - 08:00 PM; Friday: Off. Expertise includes Robotic Calipers / Injections, Spine 3D Printing, Keyhole-Sutureless Spinal surgeries, Spine Dynamic stabilisation Non Fusional spine surgical Technique, Regenerative Technique Epidural Transforaminal Injection Facetal Injection, Spinal Rehabilitation Technique.For more information about Mirpur General Hospital and Diagnostic Center, please visit https://www.doctorspedia.co/hospital/mirpur-general-hospital-and-diagnostic-center",
    "metadata": {
      "id": "67fe041313b6d75e7dd157b6",
      "name": "Dr. Lt. Col. Md. Mahbub Ali",
      "specialization": "Orthopedic Surgeon",
      "yoe": 15,
      "tags": "['Robotic Calipers / Injections', 'Spine 3D Printing', 'Keyhole-Sutureless Spinal surgeries', 'Spine Dynamic stabilisation Non Fusional spine surgical Technique', 'Regenerative Technique Epidural Transforaminal Injection Facetal Injection', 'Spinal Rehabilitation Technique']",
      "designation": "MBBS, MS (Ortho Surgery)",
      "hospital": "Mirpur General Hospital and Diagnostic Center",
      "hospital_address": "R#10, H#16, Rupnogor Residential Area, Beside of Monipur School), Mirpur, Dhaka., Mirpur, Dhaka, 1216, Bangladesh",
      "hospital_url": "https://www.doctorspedia.co/hospital/mirpur-general-hospital-and-diagnostic-center",
      "availability": "['Saturday to Thursday: 06:00 PM - 08:00 PM', 'Friday: Off']"
    }
  },
  {
    "text": "Dr. Nurul Alam Siddique Pavel is a Orthopedic Surgeon with 14 years of experience. He holds the qualifications MBBS (Dhaka), D-Ortho (NITOR), BCS (Health). Currently practicing at Mirpur General Hospital and Diagnostic Center located at R#10, H#16, Rupnogor Residential Area, Beside of Monipur School), Mirpur, Dhaka., Mirpur, Dhaka, 1216, Bangladesh. Availability: Saturday to Thursday: 06:00 PM - 09:00 PM; Friday: Off. Expertise includes Facetal Injection, Robotic Calipers / Injections, Congenital and acquired deformity correction, Back Pain Treatment, Neck Pain Treatment, Spinal Cord Injury Treatment, General Orthopedic Clinic, Epidural Transforaminal Injection.For more information about Mirpur General Hospital and Diagnostic Center, please visit https://www.doctorspedia.co/hospital/mirpur-general-hospital-and-diagnostic-center",
    "metadata": {
      "id": "67fe041313b6d75e7dd157b7",
      "name": "Dr. Nurul Alam Siddique Pavel",
      "specialization": "Orthopedic Surgeon",
      "yoe": 14,
      "tags": "['Facetal Injection', 'Robotic Calipers / Injections', 'Congenital and acquired deformity correction', 'Back Pain Treatment', 'Neck Pain Treatment', 'Spinal Cord Injury Treatment', 'General Orthopedic Clinic', 'Epidural Transforaminal Injection']",
      "designation": "MBBS (Dhaka), D-Ortho (NITOR), BCS (Health)",
      "hospital": "Mirpur General Hospital and Diagnostic Center",
      "hospital_address": "R#10, H#16, Rupnogor Residential Area, Beside of Monipur School), Mirpur, Dhaka., Mirpur, Dhaka, 1216, Bangladesh",
      "hospital_url": "https://www.doctorspedia.co/hospital/mirpur-general-hospital-and-diagnostic-center",
      "availability": "['Saturday to Thursday: 06:00 PM - 09:00 PM', 'Friday: Off']"
    }
  }
]